SendEmail/SendEmail.py
SendEmail/__init__.py
EmailSender_jma-0.0.1.dist-info/LICENSE
EmailSender_jma-0.0.1.dist-info/METADATA
EmailSender_jma-0.0.1.dist-info/WHEEL
EmailSender_jma-0.0.1.dist-info/top_level.txt
EmailSender_jma-0.0.1.dist-info/RECORD
